folan.py
folan-2.0.0.dist-info/LICENSE
folan-2.0.0.dist-info/METADATA
folan-2.0.0.dist-info/WHEEL
folan-2.0.0.dist-info/entry_points.txt
folan-2.0.0.dist-info/top_level.txt
folan-2.0.0.dist-info/RECORD
